kubegpt/__init__.py
kubegpt/__main__.py
kubegpt/prompt.py
kubegpt-0.0.7.dist-info/LICENSE
kubegpt-0.0.7.dist-info/METADATA
kubegpt-0.0.7.dist-info/WHEEL
kubegpt-0.0.7.dist-info/entry_points.txt
kubegpt-0.0.7.dist-info/top_level.txt
kubegpt-0.0.7.dist-info/RECORD
