Metadata-Version: 2.1
Name: kubegpt
Version: 0.0.7
Summary: Using human language to interact with Kubernetes
Home-page: https://github.com/xeol-io/kubegpt
Author: Benji Visser
Author-email: benji@xeol.io
License: MIT
Requires-Python: >=3.9
License-File: LICENSE
Requires-Dist: openai
Requires-Dist: langchain
